jsbeautifier/__init__.py
jsbeautifier/__version__.py
jsbeautifier/cli/__init__.py
jsbeautifier/core/__init__.py
jsbeautifier/core/directives.py
jsbeautifier/core/inputscanner.py
jsbeautifier/core/options.py
jsbeautifier/core/output.py
jsbeautifier/core/pattern.py
jsbeautifier/core/templatablepattern.py
jsbeautifier/core/token.py
jsbeautifier/core/tokenizer.py
jsbeautifier/core/tokenstream.py
jsbeautifier/core/whitespacepattern.py
jsbeautifier/javascript/__init__.py
jsbeautifier/javascript/acorn.py
jsbeautifier/javascript/beautifier.py
jsbeautifier/javascript/options.py
jsbeautifier/javascript/tokenizer.py
jsbeautifier/tests/__init__.py
jsbeautifier/tests/testindentation.py
jsbeautifier/tests/generated/__init__.py
jsbeautifier/tests/generated/tests.py
jsbeautifier/unpackers/__init__.py
jsbeautifier/unpackers/evalbased.py
jsbeautifier/unpackers/javascriptobfuscator.py
jsbeautifier/unpackers/myobfuscate.py
jsbeautifier/unpackers/packer.py
jsbeautifier/unpackers/urlencode.py
jsbeautifier/unpackers/tests/__init__.py
jsbeautifier/unpackers/tests/testjavascriptobfuscator.py
jsbeautifier/unpackers/tests/testmyobfuscate.py
jsbeautifier/unpackers/tests/testpacker.py
jsbeautifier/unpackers/tests/testurlencode.py
jsbeautifier-1.15.2.dist-info/METADATA
jsbeautifier-1.15.2.dist-info/WHEEL
jsbeautifier-1.15.2.dist-info/entry_points.txt
jsbeautifier-1.15.2.dist-info/top_level.txt
jsbeautifier-1.15.2.dist-info/RECORD
